.gitignore
LICENSE
README.rst
setup.py
flask_restlib/__init__.py
flask_restlib.egg-info/PKG-INFO
flask_restlib.egg-info/SOURCES.txt
flask_restlib.egg-info/dependency_links.txt
flask_restlib.egg-info/requires.txt
flask_restlib.egg-info/top_level.txt