Metadata-Version: 1.1
Name: flask-restlib
Version: 0.1.dev1
Summary: Another extension for REST API.
Home-page: https://github.com/kyzima-spb/flask-restlib
Author: Kirill Vercetti
Author-email: office@kyzima-spb.com
License: MIT
Platform: UNKNOWN
Classifier: Environment :: Web Environment
Classifier: Intended Audience :: Developers
Classifier: Operating System :: OS Independent
Classifier: Programming Language :: Python
Classifier: Framework :: Flask
Classifier: Development Status :: 3 - Alpha
Classifier: Topic :: Internet :: WWW/HTTP
Classifier: Topic :: Internet :: WWW/HTTP :: Dynamic Content
